{
	"icon-test": 58880,
	"wenzibeijingyanse": 58881,
	"chazhao": 58882,
	"zuoye": 58883,
	"dili": 58884,
	"kexue": 58885,
	"shuxue": 58886,
	"x#1": 58887,
	"zhengzhi": 58888,
	"huaxue": 58889,
	"yuwen": 58890,
	"yingyu": 58891,
	"shengwu": 58892,
	"wuli": 58893,
	"lishi": 58894,
	"iconfont7": 58895,
	"jiantou-copy-copy": 58896,
	"luyinzanting": 58897,
	"22gouxuanduihao": 58898,
	"dui": 58899,
	"fankui": 58900,
	"zitiyanse1": 58901,
	"wenzidise": 58902,
	"rotate": 58903,
	"youxuanzhuan": 58904,
	"ask-fill": 58905,
	"icon-test1": 58906,
	"delete": 58907,
	"bandui": 58908,
	"404": 58909,
	"banji": 58910,
	"kaoshicishubiaoqian": 58911,
	"bianji": 58912,
	"shanchu": 58913,
	"kaoshizhuangtai": 58914,
	"nianji": 58915,
	"shangyiye": 58916,
	"sousuo": 58917,
	"shijuanguanbi": 58918,
	"renwuxiaotubiao": 58919,
	"shengyinbofang": 58920,
	"xueqi": 58921,
	"zhankai_m": 58922,
	"shouqi": 58923,
	"ai-img": 58924,
	"icon_search": 58925,
	"wendang": 58926,
	"wenzibeijing": 58927,
	"caidan": 58928,
	"fangda": 58929,
	"suoxiao1": 58930,
	"suoxucailiao": 58931,
	"fangdajing": 58932,
	"a": 58933,
	"xin": 58934,
	"jiantou": 58935,
	"huabi": 58936,
	"arrow-top-copy": 58937,
	"tuoyuan": 58938,
	"xuanzhuan": 58939,
	"yuwen1": 58940,
	"iconfontpaixingbang": 58941,
	"cuowu": 58942,
	"wenjian": 58943,
	"kaoshi": 58944,
	"lianxi": 58945,
	"zuoye1": 58946,
	"jinggao": 58947,
	"bbg_shenglvedianicon-more": 58948,
	"icon": 58953,
	"lianxice-": 58956,
	"xinghao": 58957,
	"xiaojiantouxia": 58958,
	"yuanjiao-rect": 58959,
	"iconphoto": 58960,
	"weizhituodong": 58961,
	"wenziyangshi": 58962,
	"tupian": 58963,
	"cuohao": 58969,
	"zitibeijingse": 58970,
	"tianjiawenjianjia": 58977,
	"bi40qietuzitibeijing": 58980,
	"x": 120,
	"wendang1": 59002,
	"wenjianjia": 59003,
	"guanbi": 59006,
	"shuangjiantou": 59027,
	"zuozhuan": 59074,
	"youzhuan": 59075,
	"luyinzanting1": 59084,
	"suoxiao": 59426,
	"luyin2": 59093,
	"icon-": 59103,
	"square-o": 59190,
	"tupiancaijian": 59242
}